vnpy_voltrader/__init__.py
vnpy_voltrader/voltrader_datafeed.py
vnpy_voltrader-1.0.0.dist-info/LICENSE
vnpy_voltrader-1.0.0.dist-info/METADATA
vnpy_voltrader-1.0.0.dist-info/WHEEL
vnpy_voltrader-1.0.0.dist-info/top_level.txt
vnpy_voltrader-1.0.0.dist-info/RECORD
